gnss_lib_py/__init__.py
gnss_lib_py/algorithms/fde.py
gnss_lib_py/algorithms/gnss_filters.py
gnss_lib_py/algorithms/residuals.py
gnss_lib_py/algorithms/snapshot.py
gnss_lib_py/navdata/navdata.py
gnss_lib_py/navdata/operations.py
gnss_lib_py/parsers/android.py
gnss_lib_py/parsers/clk.py
gnss_lib_py/parsers/google_decimeter.py
gnss_lib_py/parsers/nmea.py
gnss_lib_py/parsers/rinex_nav.py
gnss_lib_py/parsers/rinex_obs.py
gnss_lib_py/parsers/smartloc.py
gnss_lib_py/parsers/sp3.py
gnss_lib_py/utils/constants.py
gnss_lib_py/utils/coordinates.py
gnss_lib_py/utils/dop.py
gnss_lib_py/utils/ephemeris_downloader.py
gnss_lib_py/utils/file_operations.py
gnss_lib_py/utils/filters.py
gnss_lib_py/utils/gnss_models.py
gnss_lib_py/utils/sv_models.py
gnss_lib_py/utils/time_conversions.py
gnss_lib_py/visualizations/plot_map.py
gnss_lib_py/visualizations/plot_metric.py
gnss_lib_py/visualizations/plot_skyplot.py
gnss_lib_py/visualizations/style.py
gnss_lib_py-1.0.4.dist-info/LICENSE
gnss_lib_py-1.0.4.dist-info/METADATA
gnss_lib_py-1.0.4.dist-info/WHEEL
gnss_lib_py-1.0.4.dist-info/RECORD
