Metadata-Version: 2.3
Name: gnss-lib-py
Version: 1.0.4
Summary: Modular Python tool for parsing, analyzing, and visualizing Global Navigation Satellite Systems (GNSS) data and state estimates
License: MIT
Keywords: gnss
Author: Derek Knowles
Author-email: dcknowles@stanford.edu
Requires-Python: >=3.9,<3.13
Classifier: License :: OSI Approved :: MIT License
Classifier: Operating System :: OS Independent
Classifier: Programming Language :: Python :: 3
Classifier: Programming Language :: Python :: 3.9
Classifier: Programming Language :: Python :: 3.10
Classifier: Programming Language :: Python :: 3.11
Classifier: Programming Language :: Python :: 3.12
Requires-Dist: georinex (<=1.16.1)
Requires-Dist: ipykernel (>=6.0.3,<7.0.0)
Requires-Dist: jupyter (>=1.0.0,<2.0.0)
Requires-Dist: kaleido (==0.2.1)
Requires-Dist: matplotlib (>=3.5.1,<4.0.0)
Requires-Dist: notebook (>=6.0.0)
Requires-Dist: numpy (>=2.0.0,<3.0.0)
Requires-Dist: pandas (>=2.0.0,<3.0.0)
Requires-Dist: plotly (>=5.8.0,<6.0.0)
Requires-Dist: pynmea2 (>=1.18.0,<2.0.0)
Requires-Dist: pytest (>=7.2)
Requires-Dist: requests (>=2.29.0,<3.0.0)
Requires-Dist: scipy (>=1.7.3,<2.0.0)
Requires-Dist: unlzw3 (>=0.2.1,<0.3.0)
Project-URL: Documentation, https://gnss-lib-py.readthedocs.io/en/latest/
Project-URL: Homepage, https://github.com/Stanford-NavLab/gnss_lib_py
